notter/__init__.py
notter/cli.py
notter/constants.py
notter/context.py
notter/controller.py
notter/db_manager.py
notter/exceptions.py
notter/model.py
notter/notter.py
notter/repository.py
notter/sql_statements.py
notter/utils.py
notter/explorers/__init__.py
notter/explorers/base.py
notter/explorers/c.py
notter/explorers/go.py
notter/explorers/haskell.py
notter/explorers/java.py
notter/explorers/javascript.py
notter/explorers/kotlin.py
notter/explorers/lua.py
notter/explorers/perl.py
notter/explorers/php.py
notter/explorers/python.py
notter/explorers/r.py
notter/explorers/react.py
notter/explorers/regex.py
notter/explorers/registry.py
notter/explorers/ruby.py
notter/explorers/rust.py
notter/explorers/scala.py
notter/explorers/swift.py
notter/explorers/vue.py
notter-0.2.5.dist-info/LICENSE
notter-0.2.5.dist-info/METADATA
notter-0.2.5.dist-info/WHEEL
notter-0.2.5.dist-info/top_level.txt
notter-0.2.5.dist-info/RECORD
