Metadata-Version: 2.1
Name: notter
Version: 0.2.5
Summary: A simple note taking tool for software projects.
Home-page: https://github.com/taylandogan/notter
Author: Taylan Dogan
Author-email: Taylan Dogan <taylandogan.nl@gmail.com>
License: MIT License
Keywords: notes,todos,tracking,index
Requires-Python: >=3.10
License-File: LICENSE
Requires-Dist: click
Requires-Dist: pygments
Requires-Dist: aiofiles
Provides-Extra: dev
Requires-Dist: black; extra == "dev"
Requires-Dist: flake8; extra == "dev"
Requires-Dist: isort; extra == "dev"
Requires-Dist: mypy; extra == "dev"
Requires-Dist: coverage; extra == "dev"
Requires-Dist: pytest; extra == "dev"
Requires-Dist: pyinstaller; extra == "dev"
Requires-Dist: types-aiofiles; extra == "dev"
Provides-Extra: test
Requires-Dist: coverage; extra == "test"
Requires-Dist: pytest; extra == "test"
